{"version": "1.1.0",
 "packagesDir": ".lake/packages",
 "packages":
 [{"url": "https://github.com/leanprover-community/batteries",
   "type": "git",
   "subDir": null,
   "scope": "leanprover-community",
   "rev": "af731107d531b39cd7278c73f91c573f40340612",
   "name": "batteries",
   "manifestFile": "lake-manifest.json",
   "inputRev": "main",
   "inherited": true,
   "configFile": "lakefile.toml"},
  {"url": "https://github.com/leanprover-community/quote4",
   "type": "git",
   "subDir": null,
   "scope": "leanprover-community",
   "rev": "303b23fbcea94ac4f96e590c1cad6618fd4f5f41",
   "name": "Qq",
   "manifestFile": "lake-manifest.json",
   "inputRev": "master",
   "inherited": true,
   "configFile": "lakefile.lean"},
  {"url": "https://github.com/leanprover-community/aesop",
   "type": "git",
   "subDir": null,
   "scope": "leanprover-community",
   "rev": "5dfdc66e0d503631527ad90c1b5d7815c86a8662",
   "name": "aesop",
   "manifestFile": "lake-manifest.json",
   "inputRev": "master",
   "inherited": true,
   "configFile": "lakefile.toml"},
  {"url": "https://github.com/leanprover-community/ProofWidgets4",
   "type": "git",
   "subDir": null,
   "scope": "leanprover-community",
   "rev": "1383e72b40dd62a566896a6e348ffe868801b172",
   "name": "proofwidgets",
   "manifestFile": "lake-manifest.json",
   "inputRev": "v0.0.46",
   "inherited": true,
   "configFile": "lakefile.lean"},
  {"url": "https://github.com/leanprover/lean4-cli",
   "type": "git",
   "subDir": null,
   "scope": "leanprover",
   "rev": "726b3c9ad13acca724d4651f14afc4804a7b0e4d",
   "name": "Cli",
   "manifestFile": "lake-manifest.json",
   "inputRev": "main",
   "inherited": true,
   "configFile": "lakefile.toml"},
  {"url": "https://github.com/leanprover-community/import-graph",
   "type": "git",
   "subDir": null,
   "scope": "leanprover-community",
   "rev": "ac7b989cbf99169509433124ae484318e953d201",
   "name": "importGraph",
   "manifestFile": "lake-manifest.json",
   "inputRev": "main",
   "inherited": true,
   "configFile": "lakefile.toml"},
  {"url": "https://github.com/leanprover-community/LeanSearchClient",
   "type": "git",
   "subDir": null,
   "scope": "leanprover-community",
   "rev": "86d0d0584f5cd165353e2f8a30c455cd0e168ac2",
   "name": "LeanSearchClient",
   "manifestFile": "lake-manifest.json",
   "inputRev": "main",
   "inherited": true,
   "configFile": "lakefile.toml"},
  {"url": "https://github.com/leanprover-community/plausible",
   "type": "git",
   "subDir": null,
   "scope": "leanprover-community",
   "rev": "42dc02bdbc5d0c2f395718462a76c3d87318f7fa",
   "name": "plausible",
   "manifestFile": "lake-manifest.json",
   "inputRev": "main",
   "inherited": true,
   "configFile": "lakefile.toml"},
  {"url": "https://github.com/leanprover-community/mathlib4.git",
   "type": "git",
   "subDir": null,
   "scope": "",
   "rev": "1964227ee4bc4a748a0fd3b7538fb3624bd53cdf",
   "name": "mathlib",
   "manifestFile": "lake-manifest.json",
   "inputRev": null,
   "inherited": false,
   "configFile": "lakefile.lean"},
  {"url": "https://github.com/PatrickMassot/checkdecls.git",
   "type": "git",
   "subDir": null,
   "scope": "",
   "rev": "11fa569b1b52f987dc5dcea97fd80eaff95c2fce",
   "name": "checkdecls",
   "manifestFile": "lake-manifest.json",
   "inputRev": null,
   "inherited": false,
   "configFile": "lakefile.lean"},
  {"url": "https://github.com/acmepjz/md4lean",
   "type": "git",
   "subDir": null,
   "scope": "",
   "rev": "5e95f4776be5e048364f325c7e9d619bb56fb005",
   "name": "MD4Lean",
   "manifestFile": "lake-manifest.json",
   "inputRev": "main",
   "inherited": true,
   "configFile": "lakefile.lean"},
  {"url": "https://github.com/fgdorais/lean4-unicode-basic",
   "type": "git",
   "subDir": null,
   "scope": "",
   "rev": "b41bc9cec7f433d6e1d74ff3b59edaaf58ad2915",
   "name": "UnicodeBasic",
   "manifestFile": "lake-manifest.json",
   "inputRev": "main",
   "inherited": true,
   "configFile": "lakefile.lean"},
  {"url": "https://github.com/dupuisf/BibtexQuery",
   "type": "git",
   "subDir": null,
   "scope": "",
   "rev": "bdc2fc30b1e834b294759a5d391d83020a90058e",
   "name": "BibtexQuery",
   "manifestFile": "lake-manifest.json",
   "inputRev": "master",
   "inherited": true,
   "configFile": "lakefile.lean"},
  {"url": "https://github.com/leanprover/doc-gen4",
   "type": "git",
   "subDir": null,
   "scope": "",
   "rev": "e18c6c23dd7cb1f12d79d6304262351df943aa37",
   "name": "«doc-gen4»",
   "manifestFile": "lake-manifest.json",
   "inputRev": "main",
   "inherited": false,
   "configFile": "lakefile.lean"}],
 "name": "FLT",
 "lakeDir": ".lake"}
